market_analy/__init__.py
market_analy/_version.py
market_analy/analysis.py
market_analy/cases.py
market_analy/charts.py
market_analy/config.py
market_analy/formatters.py
market_analy/gui_parts.py
market_analy/guis.py
market_analy/standalone.py
market_analy/trends_alt.py
market_analy/trends/__init__.py
market_analy/trends/analy.py
market_analy/trends/charts.py
market_analy/trends/guis.py
market_analy/trends/movements.py
market_analy/utils/__init__.py
market_analy/utils/bq_utils.py
market_analy/utils/dict_utils.py
market_analy/utils/ipyvuetify_utils.py
market_analy/utils/ipywidgets_utils.py
market_analy/utils/list_utils.py
market_analy/utils/maths_utils.py
market_analy/utils/mkt_prices_utils.py
market_analy/utils/pandas_utils.py
market_analy-0.6.2.dist-info/licenses/LICENSE.txt
market_analy-0.6.2.dist-info/METADATA
market_analy-0.6.2.dist-info/WHEEL
market_analy-0.6.2.dist-info/top_level.txt
market_analy-0.6.2.dist-info/RECORD
