Metadata-Version: 2.4
Name: market_analy
Version: 0.6.2
Summary: Analysis of exchange-listed financial instruments
Author: Marcus Read
Author-email: marcusaread.prog@proton.me
License-Expression: MIT
Project-URL: homepage, https://github.com/maread99/market_analy
Project-URL: documentation, https://github.com/maread99/market_analy
Project-URL: Issue Tracker, https://github.com/maread99/market_analy/issues
Project-URL: Source Code, https://github.com/maread99/market_analy
Keywords: finance,analysis,prices,historical-data,investing,stocks,currencies,forex,crypto,etf,funds,bonds,commodities,indices
Classifier: Development Status :: 4 - Beta
Classifier: Intended Audience :: Developers
Classifier: Intended Audience :: Education
Classifier: Intended Audience :: Financial and Insurance Industry
Classifier: Intended Audience :: Science/Research
Classifier: Natural Language :: English
Classifier: Operating System :: OS Independent
Classifier: Programming Language :: Python
Classifier: Programming Language :: Python :: 3
Classifier: Programming Language :: Python :: 3 :: Only
Classifier: Programming Language :: Python :: 3.10
Classifier: Programming Language :: Python :: 3.11
Classifier: Programming Language :: Python :: 3.12
Classifier: Programming Language :: Python :: 3.13
Classifier: Programming Language :: Python :: Implementation :: CPython
Classifier: Topic :: Office/Business :: Financial :: Accounting
Requires-Python: <4,>=3.10
License-File: LICENSE.txt
Requires-Dist: bqplot
Requires-Dist: exchange-calendars
Requires-Dist: Jinja2
Requires-Dist: market-prices
Requires-Dist: matplotlib
Requires-Dist: numpy
Requires-Dist: pandas
Requires-Dist: traitlets
Requires-Dist: tzdata
Requires-Dist: ipyvuetify
Requires-Dist: ipywidgets
Provides-Extra: jupyter
Requires-Dist: jupyter; extra == "jupyter"
Requires-Dist: jupyterlab>=3.0; extra == "jupyter"
Dynamic: license-file
